[
  {
    "title": "A Crack in the Cosmos",
    "url": "https://drb.ie/articles/a-crack-in-the-cosmos/",
    "author": "Hooke",
    "date": "2025-09-01",
    "points": "71",
    "comments": "0",
    "discussion_url": "https://news.ycombinator.com/item?id=45080313"
  },
  {
    "title": "A Linux version of the Procmon Sysinternals tool",
    "url": "https://github.com/microsoft/ProcMon-for-Linux",
    "author": "LelouBil",
    "date": "2025-09-01",
    "points": "112",
    "comments": "0",
    "discussion_url": "https://news.ycombinator.com/item?id=45087748"
  },
  {
    "title": "A Review of Nim 2: The Good and Bad with Example Code",
    "url": "https://miguel-martin.com/blog/nim2-review",
    "author": "miguel_martin",
    "date": "2025-09-01",
    "points": "8",
    "comments": "0",
    "discussion_url": "https://news.ycombinator.com/item?id=45057734"
  },
  {
    "title": "Ask HN: Best foundation model for CLM fine-tuning?",
    "url": "https://news.ycombinator.com/item?id=45050732",
    "author": "philomath868",
    "date": "2025-09-01",
    "points": "20",
    "comments": "0",
    "discussion_url": "https://news.ycombinator.com/item?id=45050732"
  },
  {
    "title": "Bayes, Bits and Brains",
    "url": "https://bayesbitsbrains.github.io/",
    "author": "cgadski",
    "date": "2025-09-01",
    "points": "62",
    "comments": "0",
    "discussion_url": "https://news.ycombinator.com/item?id=45052191"
  },
  {
    "title": "Bidirectional Signals from the Emitter's Perspective in PHP",
    "url": "https://medium.com/@MortezaPoussane/a-new-observer-pattern-bidirectional-signals-from-the-emitters-perspective-in-php-d8a555939e15",
    "author": "mooreds",
    "date": "2025-09-01",
    "points": "4",
    "comments": "0",
    "discussion_url": "https://news.ycombinator.com/item?id=45053672"
  },
  {
    "title": "C++: Strongly Happens Before?",
    "url": "https://nekrozqliphort.github.io/posts/happens-b4/",
    "author": "signa11",
    "date": "2025-09-01",
    "points": "44",
    "comments": "0",
    "discussion_url": "https://news.ycombinator.com/item?id=45052960"
  },
  {
    "title": "Eternal Struggle",
    "url": "https://yoavg.github.io/eternal/",
    "author": "yurivish",
    "date": "2025-09-01",
    "points": "521",
    "comments": "0",
    "discussion_url": "https://news.ycombinator.com/item?id=45086020"
  },
  {
    "title": "Ford and the Birth of the Model T",
    "url": "https://www.construction-physics.com/p/ford-and-the-birth-of-the-model-t",
    "author": "chmaynard",
    "date": "2025-09-01",
    "points": "34",
    "comments": "0",
    "discussion_url": "https://news.ycombinator.com/item?id=45058349"
  },
  {
    "title": "Jujutsu for everyone",
    "url": "https://jj-for-everyone.github.io/",
    "author": "Bogdanp",
    "date": "2025-09-01",
    "points": "374",
    "comments": "0",
    "discussion_url": "https://news.ycombinator.com/item?id=45083952"
  },
  {
    "title": "Launch HN: VibeFlow (YC S25) – Web app generator with visual, editable workflows",
    "url": "https://news.ycombinator.com/item?id=45084759",
    "author": "alepeak",
    "date": "2025-09-01",
    "points": "89",
    "comments": "0",
    "discussion_url": "https://news.ycombinator.com/item?id=45084759"
  },
  {
    "title": "Lewis and Clark marked their trail with laxatives",
    "url": "https://offbeatoregon.com/2501d1006d_biliousPills-686.077.html",
    "author": "toomuchtodo",
    "date": "2025-09-01",
    "points": "159",
    "comments": "0",
    "discussion_url": "https://news.ycombinator.com/item?id=45087815"
  },
  {
    "title": "Mainframe upgrade done with wire cutters (2010)",
    "url": "https://alt.folklore.computers.narkive.com/nZagiUHj/mainframe-upgrade-done-with-wire-cutters",
    "author": "WorldPeas",
    "date": "2025-09-01",
    "points": "29",
    "comments": "0",
    "discussion_url": "https://news.ycombinator.com/item?id=45058187"
  },
  {
    "title": "National Grid: UK's largest battery storage facility at Tilbury substation",
    "url": "https://www.nationalgrid.com/national-grid-connects-uks-largest-battery-storage-facility-tilbury-substation",
    "author": "zeristor",
    "date": "2025-09-01",
    "points": "26",
    "comments": "0",
    "discussion_url": "https://news.ycombinator.com/item?id=45091119"
  },
  {
    "title": "New Ruby Curl bindings with Fiber native support",
    "url": "https://github.com/taf2/curb/blob/master/ChangeLog.md",
    "author": "taf2",
    "date": "2025-09-01",
    "points": "76",
    "comments": "0",
    "discussion_url": "https://news.ycombinator.com/item?id=45086276"
  },
  {
    "title": "Nintendo Switch 2 Dock USB-C Compatibility",
    "url": "https://www.lttlabs.com/blog/2025/08/30/nintendo-switch-2-dock",
    "author": "croes",
    "date": "2025-09-01",
    "points": "211",
    "comments": "0",
    "discussion_url": "https://news.ycombinator.com/item?id=45087971"
  },
  {
    "title": "Plastic Before Plastic: How gutta-percha shaped the 19th century",
    "url": "https://worldhistory.substack.com/p/plastic-before-plastic",
    "author": "crescit_eundo",
    "date": "2025-09-01",
    "points": "85",
    "comments": "0",
    "discussion_url": "https://news.ycombinator.com/item?id=45084193"
  },
  {
    "title": "Pong Clock",
    "url": "https://bigjobby.com/pong/?v=2.0/",
    "author": "donohoe",
    "date": "2025-09-01",
    "points": "117",
    "comments": "0",
    "discussion_url": "https://news.ycombinator.com/item?id=45054119"
  },
  {
    "title": "Show HN: Spotilyrics – See synchronized Spotify lyrics inside VS Code",
    "url": "https://github.com/therepanic/spotilyrics",
    "author": "therepanic",
    "date": "2025-09-01",
    "points": "27",
    "comments": "0",
    "discussion_url": "https://news.ycombinator.com/item?id=45087905"
  },
  {
    "title": "Survey: a third of senior developers say over half their code is AI-generated",
    "url": "https://www.fastly.com/blog/senior-developers-ship-more-ai-code",
    "author": "Brajeshwar",
    "date": "2025-09-01",
    "points": "159",
    "comments": "0",
    "discussion_url": "https://news.ycombinator.com/item?id=45083635"
  },
  {
    "title": "Telli (YC F24) is hiring engineers, designers, and interns [on-site Berlin]",
    "url": "https://hi.telli.com/join-us",
    "author": "",
    "date": "2025-09-01",
    "points": "0",
    "comments": "0",
    "discussion_url": "https://news.ycombinator.com/item?id=45090216"
  },
  {
    "title": "The Qweremin",
    "url": "https://www.linusakesson.net/qweremin/index.php",
    "author": "aebtebeten",
    "date": "2025-09-01",
    "points": "63",
    "comments": "0",
    "discussion_url": "https://news.ycombinator.com/item?id=45061702"
  },
  {
    "title": "Use One Big Server (2022)",
    "url": "https://specbranch.com/posts/one-big-server/",
    "author": "antov825",
    "date": "2025-09-01",
    "points": "218",
    "comments": "0",
    "discussion_url": "https://news.ycombinator.com/item?id=45085029"
  },
  {
    "title": "Vibe coding as a coding veteran: from 8-bit assembly to English-as-code",
    "url": "https://levelup.gitconnected.com/vibe-coding-as-a-coding-veteran-cd370fe2be50",
    "author": "thunderbong",
    "date": "2025-09-01",
    "points": "146",
    "comments": "0",
    "discussion_url": "https://news.ycombinator.com/item?id=45053764"
  },
  {
    "title": "We should have the ability to run any code we want on hardware we own",
    "url": "https://hugotunius.se/2025/08/31/what-every-argument-about-sideloading-gets-wrong.html",
    "author": "K0nserv",
    "date": "2025-09-01",
    "points": "1152",
    "comments": "0",
    "discussion_url": "https://news.ycombinator.com/item?id=45087396"
  },
  {
    "title": "What Is Complexity in Chess?",
    "url": "https://lichess.org/@/Toadofsky/blog/what-is-complexity/pKo1swFh",
    "author": "fzliu",
    "date": "2025-09-01",
    "points": "54",
    "comments": "0",
    "discussion_url": "https://news.ycombinator.com/item?id=45089256"
  },
  {
    "title": "What to do with C++ modules?",
    "url": "https://nibblestew.blogspot.com/2025/08/we-need-to-seriously-think-about-what.html",
    "author": "ingve",
    "date": "2025-09-01",
    "points": "176",
    "comments": "0",
    "discussion_url": "https://news.ycombinator.com/item?id=45086210"
  },
  {
    "title": "When the sun will literally set on what's left of the British Empire",
    "url": "https://oikofuge.com/sun-sets-on-british-empire/",
    "author": "bediger4000",
    "date": "2025-09-01",
    "points": "191",
    "comments": "0",
    "discussion_url": "https://news.ycombinator.com/item?id=45084913"
  },
  {
    "title": "Why haven't quantum computers factored 21 yet?",
    "url": "https://algassert.com/post/2500",
    "author": "ingve",
    "date": "2025-09-01",
    "points": "297",
    "comments": "0",
    "discussion_url": "https://news.ycombinator.com/item?id=45082587"
  },
  {
    "title": "“This telegram must be closely paraphrased before being communicated to anyone”",
    "url": "https://history.stackexchange.com/questions/79371/this-telegram-must-be-closely-paraphrased-before-being-communicated-to-anyone",
    "author": "azeemba",
    "date": "2025-09-01",
    "points": "664",
    "comments": "0",
    "discussion_url": "https://news.ycombinator.com/item?id=45082731"
  }
]
